cloudshovel/__init__.py
cloudshovel/main.py
cloudshovel/utils/__init__.py
cloudshovel/utils/digger.py
cloudshovel/utils/bash_scripts/install_ntfs_3g.sh
cloudshovel/utils/bash_scripts/mount_and_dig.sh
cloudshovel-1.0.2.dist-info/LICENSE
cloudshovel-1.0.2.dist-info/METADATA
cloudshovel-1.0.2.dist-info/WHEEL
cloudshovel-1.0.2.dist-info/entry_points.txt
cloudshovel-1.0.2.dist-info/top_level.txt
cloudshovel-1.0.2.dist-info/RECORD
