Metadata-Version: 2.1
Name: cloudshovel
Version: 1.0.2
Summary: A tool for digging secrets in public AMIs
Home-page: https://github.com/saw-your-packet/CloudShovel
Author: Eduard Agavriloae
Author-email: eduard.agavriloae@hacktodef.com
Keywords: aws ami secrets cloudshovel cloudquarry
Classifier: Development Status :: 4 - Beta
Classifier: Intended Audience :: Developers
Classifier: License :: OSI Approved :: Mozilla Public License 2.0 (MPL 2.0)
Classifier: Operating System :: OS Independent
Classifier: Topic :: Security
Classifier: Programming Language :: Python :: 3
Classifier: Programming Language :: Python :: 3.6
Classifier: Programming Language :: Python :: 3.7
Classifier: Programming Language :: Python :: 3.8
Classifier: Programming Language :: Python :: 3.9
Classifier: Programming Language :: Python :: 3.10
Classifier: Programming Language :: Python :: 3.11
Requires-Python: >=3.6
License-File: LICENSE
Requires-Dist: boto3
Requires-Dist: colorama
